app1/__init__.py
app1/admin.py
app1/models.py
app1/myobj.py
app1/tests.py
app1/urls.py
app1/views.py
app1/请求.py
app1/migrations/0001_initial.py
app1/migrations/__init__.py
rucicodeapi/__init__.py
rucicodeapi/lookcode.py
yzm/__init__.py
yzm/settings.py
yzm/urls.py
yzm/wsgi.py
rucicodeapi-1.1.dist-info/LICENSE
rucicodeapi-1.1.dist-info/METADATA
rucicodeapi-1.1.dist-info/WHEEL
rucicodeapi-1.1.dist-info/top_level.txt
rucicodeapi-1.1.dist-info/RECORD
