Metadata-Version: 2.1
Name: rucicodeapi
Version: 1.1
Summary: a code api.
Home-page: https://github.com/
Author: Ruci
Author-email: 178366124@qq.com
License: UNKNOWN
Platform: UNKNOWN
Classifier: Programming Language :: Python :: 3
Classifier: License :: OSI Approved :: MIT License
Classifier: Operating System :: OS Independent
Requires-Python: >=3.5
Requires-Dist: requests
